motion_vector_extractor.libs/libopencv_core-7b0a999f.so.4.12.0
motion_vector_extractor.libs/libopencv_imgproc-f647332d.so.4.12.0
mvextractor/__init__.py
mvextractor/__main__.py
mvextractor/videocap.cpython-310-x86_64-linux-gnu.so
motion_vector_extractor-2.0.0.dist-info/METADATA
motion_vector_extractor-2.0.0.dist-info/WHEEL
motion_vector_extractor-2.0.0.dist-info/entry_points.txt
motion_vector_extractor-2.0.0.dist-info/top_level.txt
motion_vector_extractor-2.0.0.dist-info/RECORD
motion_vector_extractor-2.0.0.dist-info/licenses/LICENSE
